{"languages":{"abap":{"name":"ABAP","globs":["*.abap"],"interpreters":[]},"actionscript":{"name":"ActionScript","globs":["*.as"],"interpreters":[]},"ada":{"name":"Ada","globs":["*.ada","*.adb","*.ads","*.pad"],"interpreters":[]},"agda":{"name":"Agda","globs":["*.agda"],"interpreters":[]},"alex":{"name":"Alex","globs":["*.x"],"interpreters":[]},"arduino":{"name":"Arduino C++","globs":["*.ino"],"interpreters":[]},"asciidoc":{"name":"AsciiDoc","globs":["*.adoc","*.asc","*.asciidoc"],"interpreters":[]},"asn1":{"name":"ASN.1","globs":["*.asn1"],"interpreters":[]},"asp":{"name":"ASP","globs":["*.asa","*.asp"],"interpreters":[]},"aspnet":{"name":"ASP.NET","globs":["*.asax","*.ascx","*.asmx","*.aspx","*.master","*.sitemap","*.webinfo"],"interpreters":[]},"assembly":{"name":"Assembly","globs":["*.asm"],"interpreters":[]},"assemblygas":{"name":"GNU Style Assembly","globs":["*.s"],"interpreters":[]},"autoconf":{"name":"Autoconf","globs":["*.in"],"interpreters":[]},"autohotkey":{"name":"AutoHotKey","globs":["*.ahk"],"interpreters":[]},"automake":{"name":"Automake","globs":["*.am"],"interpreters":[]},"bash":{"name":"BASH","globs":["*.bash"],"interpreters":["bash"]},"batch":{"name":"Batch","globs":["*.bat","*.btm","*.cmd"],"interpreters":[]},"brightscript":{"name":"BrightScript","globs":["*.brs"],"interpreters":[]},"c":{"name":"C","globs":["*.c","*.ec","*.pgc"],"interpreters":[]},"cabal":{"name":"Cabal","globs":["*.cabal"],"interpreters":[]},"cassius":{"name":"Cassius","globs":["*.cassius"],"interpreters":[]},"ceylon":{"name":"Ceylon","globs":["*.ceylon"],"interpreters":[]},"cheader":{"name":"C Header","globs":["*.h"],"interpreters":[]},"clojure":{"name":"Clojure","globs":["*.clj"],"interpreters":[]},"clojurec":{"name":"ClojureC","globs":["*.cljc"],"interpreters":[]},"clojurescript":{"name":"ClojureScript","globs":["*.cljs"],"interpreters":[]},"cmake":{"name":"CMake","globs":["*.cmake","cmakelists.txt"],"interpreters":[]},"cobol":{"name":"COBOL","globs":["*.cob","*.cbl","*.ccp","*.cobol","*.cpy"],"interpreters":[]},"coffeescript":{"name":"CoffeeScript","globs":["*.coffee","*.cjsx"],"interpreters":[]},"cogent":{"name":"Cogent","globs":["*.cogent"],"interpreters":[]},"coldfusion":{"name":"ColdFusion","globs":["*.cfm"],"interpreters":[]},"coldfusionscript":{"name":"ColdFusion CFScript","globs":["*.cfc"],"interpreters":[]},"coq":{"name":"Coq","globs":["*.v"],"interpreters":[]},"cpp":{"name":"C++","globs":["*.cc","*.cpp","*.cxx","*.c++","*.pcc","*.tpp"],"interpreters":[]},"cppheader":{"name":"C++ Header","globs":["*.hh","*.hpp","*.hxx","*.inl","*.ipp"],"interpreters":[]},"crystal":{"name":"Crystal","globs":["*.cr"],"interpreters":[]},"csharp":{"name":"C#","globs":["*.cs"],"interpreters":[]},"cshell":{"name":"C Shell","globs":["*.csh"],"interpreters":["csh"]},"css":{"name":"CSS","globs":["*.css"],"interpreters":[]},"cue":{"name":"CUE","globs":["*.cue"],"interpreters":[]},"d":{"name":"D","globs":["*.d"],"interpreters":[]},"dart":{"name":"Dart","globs":["*.dart"],"interpreters":[]},"devicetree":{"name":"Device Tree","globs":["*.dts","*.dtsi"],"interpreters":[]},"dhall":{"name":"Dhall","globs":["*.dhall"],"interpreters":[]},"dockerfile":{"name":"Dockerfile","globs":["*.dockerfile","*.dockerignore","dockerfile"],"interpreters":[]},"dotnetresource":{"name":".NET Resource","globs":["*.resx"],"interpreters":[]},"dreammaker":{"name":"Dream Maker","globs":["*.dm","*.dme"],"interpreters":[]},"dust":{"name":"Dust.js","globs":["*.dust"],"interpreters":[]},"edn":{"name":"Edn","globs":["*.edn"],"interpreters":[]},"elisp":{"name":"Emacs Lisp","globs":["*.el"],"interpreters":[]},"elixir":{"name":"Elixir","globs":["*.ex","*.exs"],"interpreters":[]},"elm":{"name":"Elm","globs":["*.elm"],"interpreters":[]},"elvish":{"name":"Elvish","globs":["*.elv"],"interpreters":["elvish"]},"emacsdevenv":{"name":"Emacs Dev Env","globs":["*.ede"],"interpreters":[]},"emojicode":{"name":"Emojicode","globs":["*.emojic","*.🍇"],"interpreters":[]},"erlang":{"name":"Erlang","globs":["*.erl","*.hrl"],"interpreters":[]},"fen":{"name":"FEN","globs":["*.fen"],"interpreters":[]},"fish":{"name":"Fish","globs":["*.fish"],"interpreters":["fish"]},"flatbuffers":{"name":"FlatBuffers Schema","globs":["*.fbs"],"interpreters":[]},"forth":{"name":"Forth","globs":["*.4th","*.forth","*.fr","*.frt","*.fth","*.f83","*.fb","*.fpm","*.e4","*.rx","*.ft"],"interpreters":[]},"fortranlegacy":{"name":"FORTRAN Legacy","globs":["*.f","*.for","*.ftn","*.f77","*.pfo"],"interpreters":[]},"fortranmodern":{"name":"FORTRAN Modern","globs":["*.f03","*.f08","*.f90","*.f95"],"interpreters":[]},"freemarker":{"name":"FreeMarker","globs":["*.ftl","*.ftlh","*.ftlx"],"interpreters":[]},"fsharp":{"name":"F#","globs":["*.fs","*.fsi","*.fsx","*.fsscript"],"interpreters":[]},"fstar":{"name":"F*","globs":["*.fst"],"interpreters":[]},"gdb":{"name":"GDB Script","globs":["*.gdb"],"interpreters":[]},"gdscript":{"name":"GDScript","globs":["*.gd"],"interpreters":[]},"gherkin":{"name":"Gherkin (Cucumber)","globs":["*.feature"],"interpreters":[]},"glsl":{"name":"GLSL","globs":["*.vert","*.tesc","*.tese","*.geom","*.frag","*.comp","*.glsl"],"interpreters":[]},"go":{"name":"Go","globs":["*.go"],"interpreters":[]},"graphql":{"name":"GraphQL","globs":["*.gql","*.graphql"],"interpreters":[]},"groovy":{"name":"Groovy","globs":["*.groovy","*.grt","*.gtpl","*.gvy"],"interpreters":[]},"hamlet":{"name":"Hamlet","globs":["*.hamlet"],"interpreters":[]},"handlebars":{"name":"Handlebars","globs":["*.hbs","*.handlebars"],"interpreters":[]},"happy":{"name":"Happy","globs":["*.y","*.ly"],"interpreters":[]},"haskell":{"name":"Haskell","globs":["*.hs"],"interpreters":[]},"haxe":{"name":"Haxe","globs":["*.hx"],"interpreters":[]},"hcl":{"name":"HCL","globs":["*.hcl","*.tf","*.tfvars"],"interpreters":[]},"hex":{"name":"HEX","globs":["*.hex"],"interpreters":[]},"hlsl":{"name":"HLSL","globs":["*.hlsl"],"interpreters":[]},"holyc":{"name":"HolyC","globs":["*.HC","*.hc"],"interpreters":[]},"html":{"name":"HTML","globs":["*.html","*.htm"],"interpreters":[]},"idris":{"name":"Idris","globs":["*.idr","*.lidr"],"interpreters":[]},"ini":{"name":"INI","globs":["*.ini"],"interpreters":[]},"intelhex":{"name":"Intel HEX","globs":["*.ihex"],"interpreters":[]},"isabelle":{"name":"Isabelle","globs":["*.thy"],"interpreters":[]},"jai":{"name":"JAI","globs":["*.jai"],"interpreters":[]},"java":{"name":"Java","globs":["*.java"],"interpreters":[]},"javascript":{"name":"JavaScript","globs":["*.js","*.mjs"],"interpreters":[]},"json":{"name":"JSON","globs":["*.json"],"interpreters":[]},"jsx":{"name":"JSX","globs":["*.jsx"],"interpreters":[]},"julia":{"name":"Julia","globs":["*.jl"],"interpreters":[]},"julius":{"name":"Julius","globs":["*.julius"],"interpreters":[]},"kakounescript":{"name":"Kakoune script","globs":["*.kak"],"interpreters":[]},"kotlin":{"name":"Kotlin","globs":["*.kt","*.kts"],"interpreters":[]},"lean":{"name":"Lean","globs":["*.lean","*.hlean"],"interpreters":[]},"less":{"name":"LESS","globs":["*.less"],"interpreters":[]},"linkerscript":{"name":"LD Script","globs":["*.lds"],"interpreters":[]},"liquid":{"name":"Liquid","globs":["*.liquid"],"interpreters":[]},"lisp":{"name":"Lisp","globs":["*.lisp","*.lsp"],"interpreters":[]},"llvm":{"name":"LLVM","globs":["*.ll"],"interpreters":[]},"logtalk":{"name":"Logtalk","globs":["*.lgt","*.logtalk"],"interpreters":[]},"lua":{"name":"Lua","globs":["*.lua"],"interpreters":[]},"lucius":{"name":"Lucius","globs":["*.lucius"],"interpreters":[]},"madlang":{"name":"Madlang","globs":["*.mad"],"interpreters":[]},"makefile":{"name":"Makefile","globs":["*.makefile","*.mak","*.mk","makefile"],"interpreters":[]},"markdown":{"name":"Markdown","globs":["*.md","*.markdown"],"interpreters":[]},"meson":{"name":"Meson","globs":["meson.build","meson_options.txt"],"interpreters":[]},"mint":{"name":"Mint","globs":["*.mint"],"interpreters":[]},"moduledef":{"name":"Module-Definition","globs":["*.def"],"interpreters":[]},"moonscript":{"name":"MoonScript","globs":["*.moon"],"interpreters":[]},"msbuild":{"name":"MSBuild","globs":["*.csproj","*.vbproj","*.fsproj","*.props","*.targets"],"interpreters":[]},"mustache":{"name":"Mustache","globs":["*.mustache"],"interpreters":[]},"nim":{"name":"Nim","globs":["*.nim"],"interpreters":[]},"nix":{"name":"Nix","globs":["*.nix"],"interpreters":[]},"notquiteperl":{"name":"Not Quite Perl","globs":["*.nqp"],"interpreters":[]},"objectivec":{"name":"Objective-C","globs":["*.m"],"interpreters":[]},"objectivecpp":{"name":"Objective-C++","globs":["*.mm"],"interpreters":[]},"ocaml":{"name":"OCaml","globs":["*.ml","*.mli","*.re","*.rei"],"interpreters":[]},"odin":{"name":"Odin","globs":["*.odin"],"interpreters":[]},"org":{"name":"Org","globs":["*.org"],"interpreters":[]},"oz":{"name":"Oz","globs":["*.oz"],"interpreters":[]},"pan":{"name":"Pan","globs":["*.pan","*.tpl"],"interpreters":[]},"pascal":{"name":"Pascal","globs":["*.pas","*.pp"],"interpreters":[]},"perl":{"name":"Perl","globs":["*.pl","*.pm"],"interpreters":["perl"]},"perl6":{"name":"Perl6","globs":["*.pl6","*.pm6"],"interpreters":[]},"pest":{"name":"Pest","globs":["*.pest"],"interpreters":[]},"php":{"name":"PHP","globs":["*.php"],"interpreters":[]},"polly":{"name":"Polly","globs":["*.polly"],"interpreters":[]},"pony":{"name":"Pony","globs":["*.pony"],"interpreters":[]},"postcss":{"name":"PostCSS","globs":["*.pcss","*.sss"],"interpreters":[]},"powershell":{"name":"PowerShell","globs":["*.ps1","*.psm1","*.psd1","*.ps1xml","*.cdxml","*.pssc","*.psc1"],"interpreters":[]},"processing":{"name":"Processing","globs":["*.pde"],"interpreters":[]},"prolog":{"name":"Prolog","globs":["*.p","*.pro"],"interpreters":[]},"protobuf":{"name":"Protocol Buffers","globs":["*.proto"],"interpreters":[]},"psl":{"name":"PSL Assertion","globs":["*.psl"],"interpreters":[]},"purescript":{"name":"PureScript","globs":["*.purs"],"interpreters":[]},"python":{"name":"Python","globs":["*.py","*.pyw"],"interpreters":["python","python2","python3"]},"qcl":{"name":"QCL","globs":["*.qcl"],"interpreters":[]},"qml":{"name":"QML","globs":["*.qml"],"interpreters":[]},"r":{"name":"R","globs":["*.r"],"interpreters":[]},"racket":{"name":"Racket","globs":["*.rkt"],"interpreters":[]},"rakefile":{"name":"Rakefile","globs":["*.rake","rakefile"],"interpreters":[]},"razor":{"name":"Razor","globs":["*.cshtml"],"interpreters":[]},"renpy":{"name":"Ren'Py","globs":["*.rpy"],"interpreters":[]},"restructuredtext":{"name":"ReStructuredText","globs":["*.rst"],"interpreters":[]},"ron":{"name":"Rusty Object Notation","globs":["*.ron"],"interpreters":[]},"rpmspecfile":{"name":"RPM Specfile","globs":["*.spec"],"interpreters":[]},"ruby":{"name":"Ruby","globs":["*.rb"],"interpreters":["ruby"]},"rubyhtml":{"name":"Ruby HTML","globs":["*.rhtml"],"interpreters":[]},"rust":{"name":"Rust","globs":["*.rs"],"interpreters":[]},"sass":{"name":"Sass","globs":["*.sass","*.scss"],"interpreters":[]},"scala":{"name":"Scala","globs":["*.sc","*.scala"],"interpreters":[]},"scheme":{"name":"Scheme","globs":["*.scm","*.ss"],"interpreters":[]},"scons":{"name":"Scons","globs":["sconscript","sconstruct"],"interpreters":[]},"sh":{"name":"Shell","globs":["*.sh"],"interpreters":["sh"]},"sml":{"name":"Standard ML","globs":["*.sml"],"interpreters":[]},"solidity":{"name":"Solidity","globs":["*.sol"],"interpreters":[]},"specmane":{"name":"Specman e","globs":["*.e"],"interpreters":[]},"spice":{"name":"Spice Netlist","globs":["*.ckt"],"interpreters":[]},"sql":{"name":"SQL","globs":["*.sql"],"interpreters":[]},"srecode":{"name":"SRecode Template","globs":["*.srt"],"interpreters":[]},"stratego":{"name":"Stratego/XT","globs":["*.str"],"interpreters":[]},"svg":{"name":"SVG","globs":["*.svg"],"interpreters":[]},"swift":{"name":"Swift","globs":["*.swift"],"interpreters":[]},"swig":{"name":"SWIG","globs":["*.swg","*.i"],"interpreters":[]},"systemverilog":{"name":"SystemVerilog","globs":["*.sv","*.svh"],"interpreters":[]},"tcl":{"name":"TCL","globs":["*.tcl"],"interpreters":[]},"tex":{"name":"TeX","globs":["*.tex","*.sty"],"interpreters":[]},"text":{"name":"Plain Text","globs":["*.text","*.txt"],"interpreters":[]},"thrift":{"name":"Thrift","globs":["*.thrift"],"interpreters":[]},"toml":{"name":"TOML","globs":["*.toml"],"interpreters":[]},"twig":{"name":"Twig","globs":["*.twig"],"interpreters":[]},"typescript":{"name":"TypeScript","globs":["*.ts","*.tsx"],"interpreters":[]},"unrealdevelopermarkdown":{"name":"Unreal Markdown","globs":["*.udn"],"interpreters":[]},"unrealplugin":{"name":"Unreal Plugin","globs":["*.uplugin"],"interpreters":[]},"unrealproject":{"name":"Unreal Project","globs":["*.uproject"],"interpreters":[]},"unrealscript":{"name":"Unreal Script","globs":["*.uc","*.uci","*.upkg"],"interpreters":[]},"unrealshader":{"name":"Unreal Shader","globs":["*.usf"],"interpreters":[]},"unrealshaderheader":{"name":"Unreal Shader Header","globs":["*.ush"],"interpreters":[]},"urweb":{"name":"Ur/Web","globs":["*.ur","*.urs"],"interpreters":[]},"urwebproject":{"name":"Ur/Web Project","globs":["*.urp"],"interpreters":[]},"vala":{"name":"Vala","globs":["*.vala"],"interpreters":[]},"vb6":{"name":"VB6","globs":["*.frm","*.bas","*.cls"],"interpreters":[]},"vbscript":{"name":"VBScript","globs":["*.vbs"],"interpreters":[]},"velocity":{"name":"Apache Velocity","globs":["*.vm"],"interpreters":[]},"verilog":{"name":"Verilog","globs":["*.vg","*.vh"],"interpreters":[]},"verilogargsfile":{"name":"Verilog Args File","globs":["*.irunargs","*.xrunargs"],"interpreters":[]},"vhdl":{"name":"VHDL","globs":["*.vhd","*.vhdl"],"interpreters":[]},"vimscript":{"name":"Vim Script","globs":["*.vim"],"interpreters":[]},"visualbasic":{"name":"Visual Basic","globs":["*.vb"],"interpreters":[]},"visualstudioproject":{"name":"Visual Studio Project","globs":["*.vcproj","*.vcxproj"],"interpreters":[]},"visualstudiosolution":{"name":"Visual Studio Solution","globs":["*.sln"],"interpreters":[]},"vue":{"name":"Vue","globs":["*.vue"],"interpreters":[]},"webassembly":{"name":"WebAssembly","globs":["*.wat","*.wast"],"interpreters":[]},"wolfram":{"name":"Wolfram","globs":["*.nb","*.wl"],"interpreters":[]},"xaml":{"name":"XAML","globs":["*.xaml"],"interpreters":[]},"xcodeconfig":{"name":"Xcode Config","globs":["*.xcconfig"],"interpreters":[]},"xml":{"name":"XML","globs":["*.xml"],"interpreters":[]},"xsl":{"name":"XSL","globs":["*.xsl","*.xslt"],"interpreters":[]},"xtend":{"name":"Xtend","globs":["*.xtend"],"interpreters":[]},"yaml":{"name":"YAML","globs":["*.yaml","*.yml"],"interpreters":[]},"zig":{"name":"Zig","globs":["*.zig"],"interpreters":[]},"zsh":{"name":"Zsh","globs":["*.zsh"],"interpreters":["zsh"]}}}
